AstroTransform/__init__.py
AstroTransform/coords/AltAz.py
AstroTransform/coords/__init__.py
AstroTransform/coords/hour_angle.py
AstroTransform/parse/LatLon.py
AstroTransform/parse/__init__.py
AstroTransform/time/JD.py
AstroTransform/time/__init__.py
AstroTransform/time/lst.py
tests/__init__.py
tests/test_time/__init__.py
tests/test_time/test_JD.py
AstroTransform-1.2.dist-info/LICENSE
AstroTransform-1.2.dist-info/METADATA
AstroTransform-1.2.dist-info/WHEEL
AstroTransform-1.2.dist-info/top_level.txt
AstroTransform-1.2.dist-info/RECORD
