Metadata-Version: 2.1
Name: AstroTransform
Version: 1.2
Summary: Package for astronomical transformations and calculations.
Author: David Law
Author-email: d.j.law@2021.ljmu.ac.uk
License-File: LICENSE
